sdhelper/__init__.py
sdhelper/_version.py
sdhelper/sdhelper.py
sdhelper-1.0.0.dist-info/LICENSE
sdhelper-1.0.0.dist-info/METADATA
sdhelper-1.0.0.dist-info/WHEEL
sdhelper-1.0.0.dist-info/top_level.txt
sdhelper-1.0.0.dist-info/RECORD
