Metadata-Version: 2.1
Name: sdhelper
Version: 1.0.0
Summary: A helper package for working with stable diffusion models.
Author-email: Jonas Loos <sdhelper@jloos.de>
License: MIT License
Project-URL: Homepage, https://github.com/JonasLoos/sdhelper
Requires-Python: >=3.9
License-File: LICENSE
Requires-Dist: diffusers
Requires-Dist: transformers
Requires-Dist: torch
Requires-Dist: datasets
Requires-Dist: accelerate
Requires-Dist: protobuf
Requires-Dist: sentencepiece
